{
  "name": "spec-fpspeed-ref-849",
  "base": "br-base.json",
  "workdir": "../../../",
  "host-init": "build-spec.sh fpspeed ref 849.fotonik3d_s",
  "overlay": "Speckle/build/overlay/fpspeed/ref",
  "rootfs-size": "3GiB",
  "outputs": [
    "/output",
    "/cpi/"
  ],
  "post_run_hook": "handle-results.py -d ref -s fpspeed",
  "files": [
    [
      "./Speckle/spec26-run-scripts/fpspeed.sh",
      "/"
    ]
  ],
  "jobs": [
    {
      "name": "849.fotonik3d_s",
      "command": "/fpspeed.sh 849.fotonik3d_s --copies 1"
    }
  ]
}
